email_reply_parser/__init__.py
email_reply_parser/version.py
sentry_forked_email_reply_parser-0.5.12.post1.dist-info/LICENSE
sentry_forked_email_reply_parser-0.5.12.post1.dist-info/METADATA
sentry_forked_email_reply_parser-0.5.12.post1.dist-info/WHEEL
sentry_forked_email_reply_parser-0.5.12.post1.dist-info/top_level.txt
sentry_forked_email_reply_parser-0.5.12.post1.dist-info/RECORD
